{
    "DNDConfig": null,
    "__parentReadjusting__": false,
    "_bottom_": {
        "type": "string",
        "value": "0dp"
    },
    "_height_": {
        "type": "string",
        "value": "56%"
    },
    "_left_": {
        "type": "string",
        "value": "0dp"
    },
    "_margin_": [
        0,
        0,
        0,
        0
    ],
    "_orientation_": 6,
    "_padding_": [
        0,
        0,
        0,
        0
    ],
    "_percent_": true,
    "_skin_": "s59789a4ad504c549bc82dada15e64db",
    "_width_": {
        "type": "string",
        "value": "100%"
    },
    "allboxes": [],
    "autogrowmode": 0,
    "canUpdateUI": true,
    "children": [
        "flxStoreName",
        "flxLine",
        "LblTransactionID",
        "lblAmountDrawn",
        "LblTransactionIDValue",
        "lblAmountDrawnValue",
        "flxButtons"
    ],
    "clipbounds": true,
    "containerweight": 100,
    "enablescrolling": true,
    "id": "FlxOverview",
    "info": null,
    "iscustomlayout": false,
    "isvisible": true,
    "kuid": "b9dd184cc17547c196933b6c65e200bc",
    "layouttype": 2,
    "name": "kony.ui.FlexContainer",
    "parent": "frmMerchantOverview",
    "pf": "frmMerchantOverview",
    "retaincontentalignment": false,
    "retainflexpositionproperties": false,
    "retainflowhorizontalalignment": false,
    "snapgridsize": 10,
    "snaptogrid": true,
    "wType": "FlexContainer",
    "widgetalignment": 1,
    "zindex": 1
}