{
    "@class": "com.kony.gen.viz.model.component.KVizImage2",
    "DNDConfig": null,
    "__parentReadjusting__": false,
    "_base64_": null,
    "_height_": {
        "type": "string",
        "value": "100%"
    },
    "_left_": {
        "type": "string",
        "value": "0dp"
    },
    "_margin_": [
        0,
        0,
        0,
        0
    ],
    "_padding_": [
        0,
        0,
        0,
        0
    ],
    "_skin_": "sbeabd975384414784bee76f5d74f0ef",
    "_src_": "on_boarding2.png",
    "_top_": {
        "type": "string",
        "value": "0dp"
    },
    "_width_": {
        "type": "string",
        "value": "100%"
    },
    "canUpdateUI": true,
    "containerId": true,
    "containerweight": 100,
    "context": {
        "channel": "mobile",
        "platform": "iphone",
        "templateType": "segments",
        "topLevelBox": null
    },
    "id": "Image0i3efef0fa25b41",
    "imagescalemode": 1,
    "info": null,
    "invokedProperty": "src",
    "iscustomlayout": false,
    "isvisible": true,
    "kuid": "f1b29ba769d44a89b2e0b5d9e95112d7",
    "name": "kony.ui.Image2",
    "parent": "Flex0cadccc716dc747",
    "pf": "segOnBOarding",
    "retaincontentalignment": false,
    "retainflexpositionproperties": false,
    "srcType": 1,
    "wType": "Image",
    "widgetalignment": 5,
    "zindex": 1
}